free_ssl_proxies/__init__.py
free_ssl_proxies/proxy_list.py
free_ssl_proxies-0.1.0.dist-info/LICENSE.txt
free_ssl_proxies-0.1.0.dist-info/WHEEL
free_ssl_proxies-0.1.0.dist-info/METADATA
free_ssl_proxies-0.1.0.dist-info/RECORD
